Workbook

Sheet Cover
A1: CELSIUS HOLDINGS FINANCIAL ANALYSIS Performance Evaluation & Industry Benchmarking Against Monster Beverage Corporation
A7: Prepared by: Samuel Bell
A8: Date: November 2025
A10: EXECUTIVE SUMMARY
A11: Primary Focus: Comprehensive three-year financial analysis of Celsius Holdings (2022-2024), tracking transformation from $654M loss-making startup to $1.4B profitable growth company
A12: Benchmarking Approach: Performance evaluated against Monster Beverage ($70B market cap leader) to contextualize Celsius's operational efficiency, margins, and valuation metrics within industry standards
A13: Key Finding: Celsius achieved profitability turnaround (from -$187M to +$145M net income) while doubling revenue, though operating margins remain 57% below Monster's mature benchmarks (11.5% vs 25.8%)
A14: Valuation Paradox: Despite inferior margins and being 1/6th revenue scale, Celsius has 9x valuation premium (P/E 369 vs 41), suggesting extreme growth expectations priced into current stock
A15: Investment Thesis: Analysis reveals Celsius as high-risk growth with strong momentum but questionable valuation, the Monster comparison highlights gaps that must close to justify premium
A17: Methodology: Primary analysis from Celsius 10-K filings (2022, 2024); Monster data from Yahoo Finance for comparative benchmarking

Sheet RawData
A1: Line Item | B1: 2022 | C1: 2023 | D1: 2024
A2: Income Statement
A3: Revenue | B3: 653604 | C3: 1318014 | D3: 1355630
A4: Cost of Revenue | B4: 382735 | C4: 684875 | D4: 675423
A5: Gross Profit | B5: 270869 | C5: 633139 | D5: 680207 | F5: *Negative % reflects shift from loss to profit
A6: Selling, General & Administrative Expenses | B6: 428670 | C6: 366773 | D6: 524479
A7: Operating Income (Loss) | B7: -157801 | C7: 266366 | D7: 155728 | F7: *all data from Celsius 2024, 2022 10-K
A8: Net Income (Loss) | B8: -187282 | C8: 226801 | D8: 145074
A9: Balance Sheet
A10: ASSETS
A11: Total Current Assets | B11: 917971 | C11: 1204904 | D11: 1224580
A12: Total Assets | B12: 1222069 | C12: 1536396 | D12: 1766881
A13: LIABILITIES
A14: Total Current Liabilities | B14: 161295 | C14: 276613 | D14: 365535
A15: Total Liabilities | B15: 387490 | C15: 447868 | D15: 542464
A16: EQUITY
A17: Total Stockholders' Equity | B17: 40091 | C17: 264040 | D17: 399929

Sheet Analysis
A1: Metric | B1: Formula | C1: 2022 | D1: 2023 | E1: 2024
A2: GROWTH RATES (Year-over-Year %)
A3: Revenue Growth % | B3: (New - Old) / Old | C3: N/A | D3: =(RawData!C3-RawData!B3)/RawData!B3 -> 1.0165329 | E3: =(RawData!D3-RawData!C3)/RawData!C3 -> 0.028539909
A4: Gross Profit Growth % | B4: (New - Old) / Old | C4: N/A | D4: =(RawData!C5-RawData!B5)/RawData!B5 -> 1.3374362 | E4: =(RawData!D5-RawData!C5)/RawData!C5 -> 0.074340706
A5: Net Income Growth % | B5: (New - Old) / Old | C5: N/A | D5: =(RawData!C8-RawData!B8)/RawData!B8 -> -2.2110133 | E5: =(RawData!D8-RawData!C8)/RawData!C8 -> -0.36034674
A7: PROFITABILITY MARGINS (% of Revenue)
A8: Gross Margin % | B8: Gross Profit / Revenue | C8: =RawData!B5/RawData!B3 -> 0.41442372 | D8: =RawData!C5/RawData!C3 -> 0.4803735 | E8: =RawData!D5/RawData!D3 -> 0.50176449
A9: Operating Margin % | B9: Operating Income / Revenue | C9: =RawData!B7/RawData!B3 -> -0.24143212 | D9: =RawData!C7/RawData!C3 -> 0.20209649 | E9: =RawData!D7/RawData!D3 -> 0.114875
A10: Net Margin % | B10: Net Income / Revenue | C10: =RawData!B8/RawData!B3 -> -0.28653741 | D10: =RawData!C8/RawData!C3 -> 0.17207784 | E10: =RawData!D8/RawData!D3 -> 0.10701593
A12: RETURNS
A13: ROE (Return on Equity) % | B13: Net Income / Equity | C13: =RawData!B8/RawData!B17 -> -4.6714225 | D13: =RawData!C8/RawData!C17 -> 0.85896455 | E13: =RawData!D8/RawData!D17 -> 0.36274939
A14: ROA (Return on Assets) % | B14: Net Income / Total Assets | C14: =RawData!B8/RawData!B12 -> -0.15324994 | D14: =RawData!C8/RawData!C12 -> 0.14761884 | E14: =RawData!D8/RawData!D12 -> 0.082107397
A16: LIQUIDITY
A17: Current Ratio | B17: Current Assets / Current Liabilities | C17: =RawData!B11/RawData!B14 -> 5.6912552 | D17: =RawData!C11/RawData!C14 -> 4.3559196 | E17: =RawData!D11/RawData!D14 -> 3.3501033
A19: KEY INSIGHTS
A20: 1. Revenue doubled in 2023 (101.7% growth) but decelerated sharply to 2.9% in 2024
A21: 2. Gross margins improving consistently (41% → 50%), showing pricing power
A22: 3. Net margins compressed from 17% to 11% due to OpEx growth outpacing revenue
A23: 4. Company transitioned from loss (-$187M) to strong profitability ($227M) in 2023
A24: 5. Liquidity remains very strong with 3.35x current ratio

Sheet Charts

Sheet Comparison
A1: Metric | B1: Celsius 2024 | C1: Monster 2024 | D1: Winner / Analysis | E1: Advantage
A2: GROWTH & PROFITABILITY
A3: Revenue Growth % (YoY) | B3: =Analysis!E3 -> 0.028539909 | C3: =(7492.709-7140.027)/7140.027 -> 0.049395051 | D3: =IF(B3>C3,"Celsius","Monster") -> Monster | E3: =IF(B3>C3, TEXT(B3-C3,"0.0%") & " higher", TEXT(C3-B3,"0.0%") & " higher") -> 2.1% higher
A4: Gross Margin % | B4: =Analysis!E8 -> 0.50176449 | C4: =4048.878/7492.709 -> 0.54037572 | D4: =IF(B4>C4,"Celsius","Monster") -> Monster | E4: =IF(B4>C4, TEXT(B4-C4,"0.0%") & " higher", TEXT(C4-B4,"0.0%") & " higher") -> 3.9% higher
A5: Operating Margin % | B5: =Analysis!E9 -> 0.114875 | C5: =1930.294/7492.709 -> 0.25762298 | D5: =IF(B5>C5,"Celsius","Monster") -> Monster | E5: =IF(B5>C5, TEXT(B5-C5,"0.0%") & " higher", TEXT(C5-B5,"0.0%") & " higher") -> 14.3% higher
A6: Net Margin % | B6: =Analysis!E10 -> 0.10701593 | C6: =1509/7492.709 -> 0.20139578 | D6: =IF(B6>C6,"Celsius","Monster") -> Monster | E6: =IF(B6>C6, TEXT(B6-C6,"0.0%") & " higher", TEXT(C6-B6,"0.0%") & " higher") -> 9.4% higher
A7: ROE (Return on Equity) % | B7: =Analysis!E13 -> 0.36274939 | C7: =1509/5957.718 -> 0.2532849 | D7: =IF(B7>C7,"Celsius","Monster") -> Celsius | E7: =IF(B7>C7, TEXT(B7-C7,"0.0%") & " higher", TEXT(C7-B7,"0.0%") & " higher") -> 10.9% higher
A8: VALUATION METRICS
A9: P/E Ratio | B9: 369.33 | C9: 40.56 | D9: =IF(B9<C9,"Celsius","Monster") -> Monster | E9: =IF(B9<C9, TEXT(C9-B9,"0.0") & " points cheaper", TEXT(B9-C9,"0.0") & " points cheaper") -> 328.8 points cheaper
A10: Market Cap (Billions) | B10: 11.44 | C10: 69.75 | D10: =IF(B10>C10,"Celsius (Larger)","Monster (Larger)") -> Monster (Larger) | E10: =TEXT(ABS(B10-C10),"$0.0") & "B " & IF(B10>C10,"larger","smaller") -> $58.3B smaller
A12: Overall Winner | B12: =IF(COUNTIF(D2:D8,"Celsius")>COUNTIF(D2:D8,"Monster"),"Celsius","Monster") -> Monster | C12: =COUNTIF(D2:D8,B12) & " out of " & COUNTA(D2:D8) & " metrics" -> 4 out of 5 metrics
A14: Executive Summary
A15: Investment Recommendation: | C15: =IF(COUNTIF(D3:D10,"Monster")>COUNTIF(D3:D10,"Celsius"),"BUY Monster - Superior Financial Performance","BUY Celsius - Strong Growth Potential") -> BUY Monster - Superior Financial Performance
A16: Key Strengths - Monster:
A17: 1. Higher profit margins (25.8% operating vs 11.5%)
A18: 2. Better valuation (P/E 40.56 vs 369.33)
A19: 3. Established market leader ($69.75B market cap)
A20: Key Strengths - Celsius:
A21: 1. Superior ROE (36.3% vs 25.3%)
A22: 2. Strong liquidity (3.35 current ratio)
A23: 3. High growth company in expansion phase
A25: INVESTMENT ANALYSIS CONCLUSION
A26: Monster Beverage ($69.8B market cap) demonstrates greater operational maturity compared to Celsius ($11.4B market cap), which makes sense due to their different growth stages. Monster's established market position yields 2.3x higher operating margins (25.8% vs 11.5%) and superior profitability across all metrics. However, Celsius shows characteristics of a high-growth disruptor, having a P/E premium (369x vs 41x) according to Yahoo Finance, despite being 1/6th Monster's size, showing that markets expect huge future growth. Monster's efficiency advantages (54% gross margin, 20% net margin) indicate pricing power and operational leverage that Celsius has not yet achieved. Monster appears to offer stability and proven execution, while Celsius's 36.3% ROE demonstrates efficient capital deployment despite lower absolute profitability. Monster would be the better investment for risk-averse investors looking for stable returns, while Celsius only for high-risk growth portfolios.

Sheet Sources
A1: DATA SOURCES AND METHODOLOGY
A3: Primary Sources:
A4: 1. Celsius Holdings, Inc. 10-K Annual Report (FY 2024)
A5: Source: Celsius Holdings (https://ir.celsiusholdingsinc.com/financials/annual-reports/default.aspx)
A6: Retrieved: 11/12/2025
A7: Used for: Income Statement, Balance Sheet (2022-2024)
A9: 2. Celsius Holdings, Inc. 10-K Annual Report (FY 2022)
A10: Source: Celsius Holdings (https://ir.celsiusholdingsinc.com/financials/annual-reports/default.aspx)
A11: Retreived: 11/12/2025
A12: Used for: Historical comparison baseline
A14: 3. Monster Beverage Corporation - Yahoo Finance Financials
A15: Source: https://finance.yahoo.com/quote/MNST/financials/
... A47: Created by: Samuel Bell
